[
  {
    "line": 1,
    "elements": [
      {
        "line": 3,
        "name": "valid status code of user Api",
        "description": "",
        "id": "validate-user-api;valid-status-code-of-user-api",
        "type": "scenario",
        "keyword": "Scenario",
        "steps": [
          {
            "result": {
              "duration": 891416800,
              "status": "passed"
            },
            "line": 4,
            "name": "get user status",
            "match": {
              "location": "StepDefinitions.get_user_status()"
            },
            "keyword": "Given "
          },
          {
            "result": {
              "duration": 839496000,
              "status": "passed"
            },
            "line": 5,
            "name": "The user calls the \"getuserAPI\" with the \"GET\" request",
            "match": {
              "arguments": [
                {
                  "val": "getuserAPI",
                  "offset": 20
                },
                {
                  "val": "GET",
                  "offset": 42
                }
              ],
              "location": "StepDefinitions.the_user_calls_the_something_with_the_something_request(String,String)"
            },
            "keyword": "When "
          },
          {
            "result": {
              "duration": 1489500,
              "status": "passed"
            },
            "line": 6,
            "name": "status\" in respose body is 200",
            "match": {
              "arguments": [
                {
                  "val": "200",
                  "offset": 27
                }
              ],
              "location": "StepDefinitions.status_in_respose_body_is(int)"
            },
            "keyword": "Then "
          }
        ]
      },
      {
        "line": 9,
        "name": "validate header contentType code of user Api",
        "description": "",
        "id": "validate-user-api;validate-header-contenttype-code-of-user-api",
        "type": "scenario",
        "keyword": "Scenario",
        "steps": [
          {
            "result": {
              "duration": 2411300,
              "status": "passed"
            },
            "line": 10,
            "name": "get user status",
            "match": {
              "location": "StepDefinitions.get_user_status()"
            },
            "keyword": "Given "
          },
          {
            "result": {
              "duration": 306690600,
              "status": "passed"
            },
            "line": 11,
            "name": "The user calls the \"getuserAPI\" with the \"GET\" request",
            "match": {
              "arguments": [
                {
                  "val": "getuserAPI",
                  "offset": 20
                },
                {
                  "val": "GET",
                  "offset": 42
                }
              ],
              "location": "StepDefinitions.the_user_calls_the_something_with_the_something_request(String,String)"
            },
            "keyword": "When "
          },
          {
            "result": {
              "duration": 5132400,
              "status": "passed"
            },
            "line": 12,
            "name": "header content type is json",
            "match": {
              "location": "StepDefinitions.header_content_type_is_json()"
            },
            "keyword": "Then "
          }
        ]
      },
      {
        "line": 15,
        "name": "validate the size of the response",
        "description": "",
        "id": "validate-user-api;validate-the-size-of-the-response",
        "type": "scenario",
        "keyword": "Scenario",
        "steps": [
          {
            "result": {
              "duration": 2421500,
              "status": "passed"
            },
            "line": 16,
            "name": "get user status",
            "match": {
              "location": "StepDefinitions.get_user_status()"
            },
            "keyword": "Given "
          },
          {
            "result": {
              "duration": 281596200,
              "status": "passed"
            },
            "line": 17,
            "name": "The user calls the \"getuserAPI\" with the \"GET\" request",
            "match": {
              "arguments": [
                {
                  "val": "getuserAPI",
                  "offset": 20
                },
                {
                  "val": "GET",
                  "offset": 42
                }
              ],
              "location": "StepDefinitions.the_user_calls_the_something_with_the_something_request(String,String)"
            },
            "keyword": "When "
          },
          {
            "result": {
              "duration": 423399900,
              "status": "passed"
            },
            "line": 18,
            "name": "the size of response is 10",
            "match": {
              "arguments": [
                {
                  "val": "10",
                  "offset": 24
                }
              ],
              "location": "StepDefinitions.the_size_of_response_is(int)"
            },
            "keyword": "Then "
          }
        ]
      }
    ],
    "name": "validate user API",
    "description": "",
    "id": "validate-user-api",
    "keyword": "Feature",
    "uri": "UserLibrary.feature"
  }
]